mdformat_configurable_black/__init__.py
mdformat_configurable_black/plugin.py
mdformat_configurable_black-0.0.1.dist-info/entry_points.txt
mdformat_configurable_black-0.0.1.dist-info/LICENSE
mdformat_configurable_black-0.0.1.dist-info/WHEEL
mdformat_configurable_black-0.0.1.dist-info/METADATA
mdformat_configurable_black-0.0.1.dist-info/RECORD
